LICENSE.txt
README
setup.cfg
setup.py
marketorestpython/__init__.py
marketorestpython/client.py
marketorestpython.egg-info/PKG-INFO
marketorestpython.egg-info/SOURCES.txt
marketorestpython.egg-info/dependency_links.txt
marketorestpython.egg-info/requires.txt
marketorestpython.egg-info/top_level.txt
marketorestpython/helper/__init__.py
marketorestpython/helper/exceptions.py
marketorestpython/helper/http_lib.py