Metadata-Version: 2.1
Name: marketorestpython
Version: 0.5.15
Summary: Python Client for the Marketo REST API
Home-page: https://github.com/jepcastelein/marketo-rest-python
Author: Jep Castelein
Author-email: jep@castelein.net
License: MIT License
Keywords: Marketo,REST API,Wrapper,Client
Platform: UNKNOWN
License-File: LICENSE.txt
